full-adder/fulladder.v
/* 
Full Adder Module for bit Addition 
Written by referencedesigner.com 
*/
module fulladder
(
 input x,
 input y,
 input cin,
 
 output A, 
 output cout
 );
 
assign {cout,A} =  cin + y + x;
 
endmodule

full-adder/fulladdertb.v
/* 
Full Adder Module for bit Addition 
Written by referencedesigner.com 
*/
`timescale 1ns / 100ps 
 
module fulladdertb; 
 
reg input1;
reg input2;
reg carryin;
 
wire out;
wire carryout;
 
 
fulladder uut (
.x(input1),
.y(input2),
.cin(carryin),
.A(out),
.cout(carryout)
);
 
initial begin
	$dumpfile("test.vcd");
    $dumpvars(0,fulladdertb);
input1 =0;
input2 =0;
carryin =0;
#20; input1 =1;
#20; input2 =1;
#20; input1 =0;
#20; carryin =1;
#20; input2=0;
#20; input1=1; 
#20; input2=1;
#40;
end
 
 
initial
begin
$monitor("time = %2d, CIN =%1b, IN1=%1b, IN2=%1b, COUT=%1b, OUT=%1b", $time,carryin,input2, input1,carryout,out);
end
 
endmodule

full-adder/test.vcd
$date
	Sun Mar 19 17:50:09 2023
$end
$version
	Icarus Verilog
$end
$timescale
	100ps
$end
$scope module fulladdertb $end
$var wire 1 ! out $end
$var wire 1 " carryout $end
$var reg 1 # carryin $end
$var reg 1 $ input1 $end
$var reg 1 % input2 $end
$scope module uut $end
$var wire 1 # cin $end
$var wire 1 $ x $end
$var wire 1 % y $end
$var wire 1 " cout $end
$var wire 1 ! A $end
$upscope $end
$upscope $end
$enddefinitions $end
#0
$dumpvars
0%
0$
0#
0"
0!
$end
#200
1!
1$
#400
0!
1"
1%
#600
1!
0"
0$
#800
0!
1"
1#
#1000
1!
0"
0%
#1200
0!
1"
1$
#1400
1!
1%
